structRFM/__init__.py
structRFM/infer.py
structRFM/pretrain.py
structRFM/data/RNAdata.py
structRFM/data/__init__.py
structRFM/data/collator.py
structRFM/data/tokenizer.py
structRFM/data/tokenizer_ar.json
structRFM/data/tokenizer_mlm.json
structRFM/model/__init__.py
structRFM/model/structRFM.py
structRFM/util/MUSES.py
structRFM/util/__init__.py
structRFM/util/misc.py
structrfm-0.0.9.dist-info/licenses/LICENSE
structrfm-0.0.9.dist-info/METADATA
structrfm-0.0.9.dist-info/WHEEL
structrfm-0.0.9.dist-info/top_level.txt
structrfm-0.0.9.dist-info/RECORD
