Metadata-Version: 2.4
Name: structRFM
Version: 0.0.9
Summary: Structure-guided RNA foundation model.
Author-email: Heqin Zhu <zhuheqin1@gmail.com>
License: MIT License
Project-URL: Homepage, https://github.com/heqin-zhu/structRFM
Project-URL: Issues, https://github.com/heqin-zhu/structRFM/issues
Keywords: RNA,secondary structure,language model,tertiary structure prediction,splice site prediction,IRES identification,multi-modal language model
Classifier: Programming Language :: Python :: 3
Classifier: License :: OSI Approved :: MIT License
Classifier: Operating System :: OS Independent
Requires-Python: >=3.8
License-File: LICENSE
Dynamic: license-file
